Metadata-Version: 2.1
Name: odoo12-addon-attachment-preview
Version: 12.0.1.0.2
Summary: Preview attachments supported by Viewer.js
Home-page: UNKNOWN
Author: Therp BV,Onestein,Odoo Community Association (OCA)
Author-email: support@odoo-community.org
License: AGPL-3
Platform: UNKNOWN
Classifier: Programming Language :: Python
Classifier: Framework :: Odoo
Classifier: License :: OSI Approved :: GNU Affero General Public License v3
Requires-Python: >=3.5
Requires-Dist: odoo (<12.1dev,>=12.0a)
